{"path":"api-reference/store-management/themes/theme-configurations","templateID":0,"sharedPropsHashes":{"nav":"Z2k7O5R","sidebarTree":"jyzzw","namespace":"Zd6xn0"},"localProps":{"version":"1.3","crumbs":[{"content":"API Reference","to":"/api-reference"},{"content":"Management APIs","to":"/api-reference/store-management"},{"content":"Themes","to":"/api-reference/store-management/themes"},{"content":"Theme Configurations","to":"/api-reference/store-management/themes/theme-configurations"}],"page":{"meta":{"title":"Theme Configurations - Themes - Management APIs - API Reference","url":"/api-reference/store-management/themes/theme-configurations","description":""},"title":"Theme Configurations","parsedPath":["pages","/api-reference","data","children",2,"data","children",31,"data","children",2],"rootPagePath":"/api-reference","path":"/api-reference/store-management/themes/theme-configurations","isSubpage":true,"route":{"path":"/theme-configurations"},"data":{"blocks":[],"children":[{"title":"Get Theme Configuration","route":{"path":"/getthemesuuidconfigurations"},"config":{"sidebar":{"token":"get"}},"data":{}},{"title":"Validate Theme Configuration","route":{"path":"/postthemesuuidconfigurationsvalidate"},"config":{"sidebar":{"token":"post"}},"data":{}}]}}}}
