{"path":"api-reference/store-management/abandoned_carts_emails/abandoned-cart-emails","templateID":0,"sharedPropsHashes":{"nav":"Z2k7O5R","sidebarTree":"jyzzw","namespace":"Zd6xn0"},"localProps":{"version":"1.3","crumbs":[{"content":"API Reference","to":"/api-reference"},{"content":"Management APIs","to":"/api-reference/store-management"},{"content":"Abandoned Carts Emails (Beta)","to":"/api-reference/store-management/abandoned_carts_emails"},{"content":"Abandoned Cart Emails","to":"/api-reference/store-management/abandoned_carts_emails/abandoned-cart-emails"}],"page":{"meta":{"title":"Abandoned Cart Emails - Abandoned Carts Emails (Beta) - Management APIs - API Reference","url":"/api-reference/store-management/abandoned_carts_emails/abandoned-cart-emails","description":""},"title":"Abandoned Cart Emails","parsedPath":["pages","/api-reference","data","children",2,"data","children",1,"data","children",0],"rootPagePath":"/api-reference","path":"/api-reference/store-management/abandoned_carts_emails/abandoned-cart-emails","isSubpage":true,"route":{"path":"/abandoned-cart-emails"},"data":{"blocks":[],"children":[{"title":"Get all email templates","route":{"path":"/getabandonedcartemails"},"config":{"sidebar":{"token":"get"}},"data":{}},{"title":"Create email template","route":{"path":"/createemailtemplate"},"config":{"sidebar":{"token":"post"}},"data":{}},{"title":"Get an email template","route":{"path":"/getabandonedcartemailtemplateid"},"config":{"sidebar":{"token":"get"}},"data":{}},{"title":"Update an email template","route":{"path":"/updateabandonedcartemailsid"},"config":{"sidebar":{"token":"put"}},"data":{}},{"title":"Delete email template","route":{"path":"/deleteabandonedcartemailtemplateid"},"config":{"sidebar":{"token":"delete"}},"data":{}},{"title":"Get default email template","route":{"path":"/getdefaultabandonedcartemailtemplate"},"config":{"sidebar":{"token":"get"}},"data":{}}]}}}}
