{"path":"stencil-docs/localization","templateID":0,"sharedPropsHashes":{"nav":"Z2k7O5R","sidebarTree":"23J4Lj","namespace":"Zd6xn0"},"localProps":{"version":"1.3","crumbs":[{"content":"Stencil Docs","to":"/stencil-docs"},{"content":"Localization","to":"/stencil-docs/localization"}],"page":{"meta":{"title":"Localization - Stencil Docs","url":"/stencil-docs/localization","description":""},"title":"Localization","parsedPath":["pages","/stencil-docs","data","children",8],"rootPagePath":"/stencil-docs","path":"/stencil-docs/localization","isSubpage":true,"route":{"path":"/localization"},"data":{"blocks":[],"children":[{"title":"Localizing Stores","route":{"path":"/localizing-stores"},"data":{}},{"title":"Translation Keys","route":{"path":"/translation-keys"},"data":{}},{"title":"Translating Regions","route":{"path":"/translating-regions"},"data":{}},{"title":"Multi Language Checkout","route":{"path":"/multi-language-checkout"},"data":{}},{"title":"Localization Tutorial","route":{"path":"/localization-tutorial"},"data":{}}]}}}}
