{"path":"theme-objects/shipping_messages","templateID":0,"sharedPropsHashes":{"nav":"Z2k7O5R","sidebarTree":"Z1Es2uT","namespace":"Zd6xn0"},"localProps":{"version":"1.3","crumbs":[{"content":"Theme Object Reference","to":"/theme-objects"},{"content":"shipping_messages","to":"/theme-objects/shipping_messages"}],"page":{"meta":{"title":"shipping_messages - Theme Object Reference","url":"/theme-objects/shipping_messages","description":"\n"},"title":"shipping_messages","parsedPath":["pages","/theme-objects","data","children",38],"rootPagePath":"/theme-objects","path":"/theme-objects/shipping_messages","isSubpage":true,"route":{"path":"/shipping_messages"},"data":{"blocks":[{"type":"jsonSchema","data":{"description":"`{{shipping_messages}}` object available to `templates/pages/home.html`","type":"array","items":{"type":"string","example":"free shipping"}},"config":{},"header":{"title":"shipping_messages"}},{"type":"text","data":""}],"children":[]}}}}
