{"path":"api-reference/providers/tax-provider-api/tax-provider","templateID":0,"sharedPropsHashes":{"nav":"Z2k7O5R","sidebarTree":"jyzzw","namespace":"Zd6xn0"},"localProps":{"version":"1.3","crumbs":[{"content":"API Reference","to":"/api-reference"},{"content":"Provider APIs","to":"/api-reference/providers"},{"content":"Tax Provider API","to":"/api-reference/providers/tax-provider-api"},{"content":"Tax Provider","to":"/api-reference/providers/tax-provider-api/tax-provider"}],"page":{"meta":{"title":"Tax Provider - Tax Provider API - Provider APIs - API Reference","url":"/api-reference/providers/tax-provider-api/tax-provider","description":""},"title":"Tax Provider","parsedPath":["pages","/api-reference","data","children",3,"data","children",1,"data","children",0],"rootPagePath":"/api-reference","path":"/api-reference/providers/tax-provider-api/tax-provider","isSubpage":true,"route":{"path":"/tax-provider"},"data":{"blocks":[],"children":[{"title":"Estimate Taxes","route":{"path":"/estimate"},"config":{"sidebar":{"token":"post"}},"data":{}},{"title":"Void Tax Quote","route":{"path":"/void"},"config":{"sidebar":{"token":"post"}},"data":{}},{"title":"Commit Tax Quote","route":{"path":"/commit"},"config":{"sidebar":{"token":"post"}},"data":{}},{"title":"Adjust Tax Quote","route":{"path":"/adjust"},"config":{"sidebar":{"token":"post"}},"data":{}}]}}}}
