{"path":"api-reference/store-management/price-lists/price-lists/updatepricelist","templateID":0,"sharedPropsHashes":{"nav":"Z2k7O5R","sidebarTree":"jyzzw","namespace":"Zd6xn0"},"localProps":{"version":"1.3","crumbs":[{"content":"API Reference","to":"/api-reference"},{"content":"Management APIs","to":"/api-reference/store-management"},{"content":"Price Lists","to":"/api-reference/store-management/price-lists"},{"content":"Price Lists","to":"/api-reference/store-management/price-lists/price-lists"},{"content":"Update a Price List","to":"/api-reference/store-management/price-lists/price-lists/updatepricelist"}],"page":{"meta":{"title":"Update a Price List - Price Lists - Price Lists - Management APIs - API Reference","url":"/api-reference/store-management/price-lists/price-lists/updatepricelist","description":"Updates a Price List.\n\nAuthorization\n\nOAuth Scopes\n\n\n\nHeaders\n\n\n\nExample\n\n\n\nFor more information on Authenticating BigCommerce APIs, see: Authentication..."},"title":"Update a Price List","parsedPath":["pages","/api-reference","data","children",2,"data","children",19,"data","children",0,"data","children",4],"rootPagePath":"/api-reference","path":"/api-reference/store-management/price-lists/price-lists/updatepricelist","isSubpage":true,"route":{"path":"/updatepricelist"},"data":{"blocks":[{"type":"text","data":"Updates a *Price List*.","header":{"title":"/pricelists/{price_list_id}","subtitle":"Update a Price List","token":"put"}},{"type":"text","data":"## Authorization","config":{"classNames":["ApiOperation--securityTitle mt-10 -mb-10"]}},{"type":"accordion","data":{"children":[{"title":"apiKey - X-Auth-Token","blocks":[{"type":"text","data":"### OAuth Scopes\n|  **UI Name** | **Permission** | **Parameter** |\n| --- | --- | --- |\n|  Products | modify | `store_v2_products` |\n|  Products | read-only | `store_v2_products_read_only` |\n\n### Headers\n\n|Header|Parameter|Description|\n|-|-|-|\n|`X-Auth-Token`|`access_token `|Obtained by creating an API account or installing an app in a BigCommerce control panel.|\n\n### Example\n\n```http\nGET /stores/{$$.env.store_hash}/v3/catalog/summary\nhost: api.bigcommerce.com\nContent-Type: application/json\nX-Auth-Token: {access_token}\n```\n\n* For more information on Authenticating BigCommerce APIs, see: [Authentication](https://developer.bigcommerce.com/api-docs/getting-started/authentication). \n* **Name**: X-Auth-Token\n* **Location**: header"}]}]},"config":{"classNames":["ApiOperation--security"]}},{"type":"text","data":"## Request Parameters","config":{"classNames":["ApiOperation--requestTitle mt-10 -mb-10"]}},{"type":"accordion","data":{"children":[{"title":"1 Path Parameter","blocks":[{"type":"jsonSchema","data":{"type":"object","properties":{"price_list_id":{"type":"integer","description":"The ID of the `Price List` requested.\n","required":true}},"required":["price_list_id"]},"config":{"hideRoot":true}}]}]},"config":{"classNames":["ApiOperation--request"]}},{"type":"text","data":"## Request Body","config":{"classNames":["ApiOperation--requestBodyTitle mt-10","-mb-10"]}},{"type":"accordion","data":{"children":[{"title":"1 Example","blocks":[{"type":"tabs","data":{"children":[{"title":"application/json","blocks":[{"type":"code","data":"{\n  \"name\": \"adipisicing\",\n  \"active\": true\n}"}]}]}}]},{"title":"Schema","config":{"defaultOpen":true},"blocks":[{"type":"jsonSchema","data":{"type":"object","allOf":[{"type":"object","description":"Common Price List properties.","title":"PriceList Base","properties":{"name":{"type":"string","description":"The unique name of the Price List. Required in /POST. \n","x-required":["post"],"example":"Wholesale"},"active":{"type":"boolean","description":"Whether or not this `Price List` and its prices are active.  Defaults to `true`.\n","example":true}},"required":["name"]}],"title":"PriceList Put","description":"Update a PriceList"},"config":{"hideRoot":false}}]}]},"config":{"classNames":["ApiOperation--requestBody"]}},{"type":"text","data":"## Responses","config":{"classNames":["ApiOperation--responsesTitle mt-10 -mb-14"]}},{"type":"tabs","data":{"children":[{"title":"200","blocks":[{"type":"accordion","data":{"children":[{"title":"1 Example","blocks":[{"type":"tabs","data":{"children":[{"title":"application/json","blocks":[{"type":"code","data":"{\n  \"data\": {\n    \"id\": 2,\n    \"name\": \"BigCommerce\",\n    \"date_created\": \"2018-02-26T17:37:01Z\",\n    \"date_modified\": \"2018-09-17T18:45:17Z\",\n    \"active\": false\n  },\n  \"meta\": {}\n}"}]}]}}]},{"title":"Schema","config":{"defaultOpen":true},"blocks":[{"type":"jsonSchema","data":{"description":"PriceList Reponse returns for:\n\n* Create a PriceList\n* Get a PriceList\n* Update a PriceList","type":"object","properties":{"data":{"allOf":[{"properties":{"id":{"type":"integer","description":"The unique numeric ID of the `Price List`; increments sequentially.\n","example":3},"date_created":{"type":"string","format":"date-time","description":"The date on which the `Price List` was created.\n","example":"2018-04-05T16:05:12Z"},"date_modified":{"type":"string","format":"date-time","description":"The date on which the `Price List` was created.\n","example":"2018-04-05T16:05:12Z"}}},{"type":"object","description":"Common Price List properties.","title":"PriceList Base","properties":{"name":{"type":"string","description":"The unique name of the Price List. Required in /POST. \n","x-required":["post"],"example":"Wholesale"},"active":{"type":"boolean","description":"Whether or not this `Price List` and its prices are active.  Defaults to `true`.\n","example":true}},"required":["name"]}],"title":"Price List","type":"object"},"meta":{"type":"object","description":"Empty meta object; may be used later.","title":"Meta"}},"title":"Price List Response"}}]}]}}]},{"title":"404","blocks":[{"type":"text","data":"The resource was not found."},{"type":"accordion","data":{"children":[{"title":"Schema","config":{"defaultOpen":true},"blocks":[{"type":"jsonSchema","data":{"description":"Error payload for the BigCommerce API.","type":"object","properties":{"status":{"description":"404 HTTP status code.\n","type":"integer"},"title":{"description":"The error title describing the particular error.","type":"string"},"type":{"type":"string"},"instance":{"type":"string"}},"title":"Not Found"}}]}]}}]},{"title":"409","blocks":[{"type":"text","data":"`Price List` was in conflict with another Price List. This is the result of duplicate unique values, such as `name`."},{"type":"accordion","data":{"children":[{"title":"Schema","config":{"defaultOpen":true},"blocks":[{"type":"jsonSchema","data":{"allOf":[{"type":"object","description":"Error payload for the BigCommerce API.\n","properties":{"status":{"description":"The HTTP status code.\n","type":"integer"},"title":{"description":"The error title describing the particular error.\n","type":"string"},"type":{"type":"string"},"instance":{"type":"string"}},"title":"Base Error"},{"type":"object","properties":{"errors":{"type":"object","additionalProperties":{"type":"string"},"title":"Detailed Errors"}}}],"title":"Error Response"}}]}]}}]},{"title":"422","blocks":[{"type":"text","data":"`Price List` was not valid. This is the result of missing required fields, or of invalid data. See the response for more details."},{"type":"accordion","data":{"children":[{"title":"Schema","config":{"defaultOpen":true},"blocks":[{"type":"jsonSchema","data":{"allOf":[{"type":"object","description":"Error payload for the BigCommerce API.\n","properties":{"status":{"description":"The HTTP status code.\n","type":"integer"},"title":{"description":"The error title describing the particular error.\n","type":"string"},"type":{"type":"string"},"instance":{"type":"string"}},"title":"Base Error"},{"type":"object","properties":{"errors":{"type":"object","additionalProperties":{"type":"string"},"title":"Detailed Errors"}}}],"title":"Error Response"}}]}]}}]}]},"config":{"classNames":["ApiOperation--responses"]}},{"type":"text","data":"## Send a Test Request","config":{"classNames":["ApiOperation--tryItOutTitle mt-10 -mb-10"]}},{"type":"http","data":{"method":"put","url":"https://api.bigcommerce.com/stores/{$$.env.store_hash}/v3/pricelists/{price_list_id}","headers":{"Content-Type":"application/json","X-Auth-Token":"{$$.env.X-Auth-Token}"},"stepPathParams":{"price_list_id":""},"body":"{\n  \"name\": \"adipisicing\",\n  \"active\": true\n}"},"config":{"canvas":false,"paddedInner":false,"classNames":["ApiOperation--tryItOut"]}}],"children":[]}}}}
