{"path":"api-reference/store-management/orders/order-taxes","templateID":0,"sharedPropsHashes":{"nav":"Z2k7O5R","sidebarTree":"jyzzw","namespace":"Zd6xn0"},"localProps":{"version":"1.3","crumbs":[{"content":"API Reference","to":"/api-reference"},{"content":"Management APIs","to":"/api-reference/store-management"},{"content":"Orders v2","to":"/api-reference/store-management/orders"},{"content":"Order Taxes","to":"/api-reference/store-management/orders/order-taxes"}],"page":{"meta":{"title":"Order Taxes - Orders v2 - Management APIs - API Reference","url":"/api-reference/store-management/orders/order-taxes","description":""},"title":"Order Taxes","parsedPath":["pages","/api-reference","data","children",2,"data","children",14,"data","children",3],"rootPagePath":"/api-reference","path":"/api-reference/store-management/orders/order-taxes","isSubpage":true,"route":{"path":"/order-taxes"},"data":{"blocks":[],"children":[{"title":"Get All Order Taxes","route":{"path":"/getordertaxes"},"config":{"sidebar":{"token":"get"}},"data":{}}]}}}}
